PyOPUS-0.9.dist-info/DESCRIPTION.rst
PyOPUS-0.9.dist-info/METADATA
PyOPUS-0.9.dist-info/RECORD
PyOPUS-0.9.dist-info/WHEEL
PyOPUS-0.9.dist-info/entry_points.txt
PyOPUS-0.9.dist-info/metadata.json
PyOPUS-0.9.dist-info/top_level.txt
pyopus/__init__.py
pyopus/design/__init__.py
pyopus/design/cbd.py
pyopus/design/mc.py
pyopus/design/sensitivity.py
pyopus/design/sqlite.py
pyopus/design/wc.py
pyopus/design/wcd.py
pyopus/design/yt.py
pyopus/evaluator/__init__.py
pyopus/evaluator/aggregate.py
pyopus/evaluator/auxfunc.py
pyopus/evaluator/measure.py
pyopus/evaluator/performance.py
pyopus/evaluator/posteval.py
pyopus/gui/__init__.py
pyopus/gui/cbddump.py
pyopus/gui/cbdnew.py
pyopus/gui/cbdrun.py
pyopus/gui/clipboard.py
pyopus/gui/daemonize.py
pyopus/gui/delegates.py
pyopus/gui/dumptools.py
pyopus/gui/editanalyses.py
pyopus/gui/editanalysis.py
pyopus/gui/editbase.py
pyopus/gui/editcbdcorner.py
pyopus/gui/editcbdcorners.py
pyopus/gui/editcbddesignpar.py
pyopus/gui/editcbdoutput.py
pyopus/gui/editcbdreq.py
pyopus/gui/editcbdsettings.py
pyopus/gui/editdesignpar.py
pyopus/gui/editfile.py
pyopus/gui/editfiles.py
pyopus/gui/editgroup.py
pyopus/gui/edithead.py
pyopus/gui/editheads.py
pyopus/gui/editinfo.py
pyopus/gui/editmeasure.py
pyopus/gui/editmeasures.py
pyopus/gui/editmpi.py
pyopus/gui/editnone.py
pyopus/gui/editoppar.py
pyopus/gui/editpostaxes.py
pyopus/gui/editpostplot.py
pyopus/gui/editpostplots.py
pyopus/gui/editposttrace.py
pyopus/gui/editselection.py
pyopus/gui/editstatpar.py
pyopus/gui/edittask.py
pyopus/gui/editvar.py
pyopus/gui/editvars.py
pyopus/gui/fileview.py
pyopus/gui/fixproject.py
pyopus/gui/fstools.py
pyopus/gui/guiglobals.py
pyopus/gui/hostseditor.py
pyopus/gui/indicators.py
pyopus/gui/launcher.py
pyopus/gui/logger.py
pyopus/gui/logscan.py
pyopus/gui/logview.py
pyopus/gui/mainwindow.py
pyopus/gui/mpidump.py
pyopus/gui/postdump.py
pyopus/gui/resbase.py
pyopus/gui/rescbdcor.py
pyopus/gui/rescbdcost.py
pyopus/gui/rescbdpar.py
pyopus/gui/rescbdperf.py
pyopus/gui/resources.py
pyopus/gui/respostbase.py
pyopus/gui/respostmeas.py
pyopus/gui/respostplot.py
pyopus/gui/restext.py
pyopus/gui/restree.py
pyopus/gui/resview.py
