Metadata-Version: 1.0
Name: PyOPUS
Version: 0.9
Summary: A simulation-based design optimization library
Home-page: http://fides.fe.uni-lj.si/pyopus/
Author: Árpád Bűrmen
Author-email: arpadb@fides.fe.uni-lj.si
License: GPL V3
Platform: Linux
Platform: Windows
